better_requests/__init__.py
better_requests/__version__.py
better_requests/api.py
better_requests/sessions.py
better_requests-1.0.1.dist-info/LICENSE
better_requests-1.0.1.dist-info/METADATA
better_requests-1.0.1.dist-info/WHEEL
better_requests-1.0.1.dist-info/top_level.txt
better_requests-1.0.1.dist-info/RECORD
