Metadata-Version: 2.1
Name: better-requests
Version: 1.0.1
Summary: HTTP for Humans that do right
Home-page: https://github.com/better-requests/better-requests
Author: better-requests
Author-email: better-requests@users.noreply.github.com
License: Apache License v2
Platform: UNKNOWN
Classifier: Development Status :: 5 - Production/Stable
Classifier: Intended Audience :: Developers
Classifier: Natural Language :: English
Classifier: License :: OSI Approved :: Apache Software License
Classifier: Programming Language :: Python
Classifier: Programming Language :: Python :: 2.7
Classifier: Programming Language :: Python :: 3
Classifier: Programming Language :: Python :: 3.4
Classifier: Programming Language :: Python :: 3.5
Requires-Dist: requests (>=1.2.0)
